{"bases_button-group.md":"-NjzRqE8","bases_button.md":"AcbORfkv","bases_colors.md":"C7VsDJ7Y","bases_icon.md":"Cj8ILQAi","bases_space.md":"BWAPLWQ-","config_start.md":"BtZNK1qm","config_theme.md":"B75NNAwC","feedback_alert.md":"7RemNZkO","feedback_dialog.md":"B7zT8MrG","form_input.md":"5g3XzgeC","index.md":"BeEkEDSm","zh-cn_bases_button-group.md":"Bxp7kTSs","zh-cn_bases_button.md":"OdwXe5lR","zh-cn_bases_colors.md":"BMcRFgvD","zh-cn_bases_icon.md":"CuVGKAkR","zh-cn_bases_space.md":"Uko1jKg2","zh-cn_config_start.md":"Dl5a96Aq","zh-cn_config_theme.md":"DMnWekQa","zh-cn_feedback_alert.md":"Dnf-7Rz_","zh-cn_feedback_dialog.md":"Dsqu-8fY","zh-cn_form_input.md":"BaCTpCTZ","zh-cn_index.md":"D4n-hLZ7"}
